setup.py
digStylometry/Stylometry.py
digStylometry/__init__.py
digStylometry/test.py
digStylometry.egg-info/PKG-INFO
digStylometry.egg-info/SOURCES.txt
digStylometry.egg-info/dependency_links.txt
digStylometry.egg-info/requires.txt
digStylometry.egg-info/top_level.txt