Metadata-Version: 1.1
Name: digStylometry
Version: 0.1.6
Summary: code to get signature to do stylometric analysis
Home-page: https://github.com/usc-isi-i2/dig-stylometry
Author: Rajagopal
Author-email: bojanapa@usc.edu
License: UNKNOWN
Download-URL: https://github.com/usc-isi-i2/dig-stylometry.git
Platform: UNKNOWN
